{
    "no": 38,
    "maxWaterInTube": 4,
    "map": [
        {
            "values": [
                9,
                9,
                4,
                2
            ]
        },
        {
            "values": [
                3,
                5,
                8,
                6
            ]
        },
        {
            "values": [
                7,
                2,
                1,
                4
            ]
        },
        {
            "values": [
                6,
                3,
                1,
                1
            ]
        },
        {
            "values": [
                7,
                8,
                5,
                5
            ]
        },
        {
            "values": [
                2,
                2,
                7,
                3
            ]
        },
        {
            "values": [
                5,
                8,
                6,
                1
            ]
        },
        {
            "values": [
                6,
                4,
                3,
                7
            ]
        },
        {
            "values": [
                9,
                8,
                4,
                9
            ]
        },
        {
            "values": []
        },
        {
            "values": []
        }
    ]
}