{
    "no": 235,
    "maxWaterInTube": 4,
    "map": [
        {
            "values": [
                4,
                1,
                4,
                1
            ]
        },
        {
            "values": [
                10,
                1,
                2,
                9
            ]
        },
        {
            "values": [
                10,
                7,
                6,
                6
            ]
        },
        {
            "values": [
                5,
                4,
                2,
                8
            ]
        },
        {
            "values": [
                7,
                8,
                3,
                2
            ]
        },
        {
            "values": [
                9,
                10,
                4,
                8
            ]
        },
        {
            "values": [
                5,
                6,
                9,
                10
            ]
        },
        {
            "values": [
                5,
                7,
                3,
                7
            ]
        },
        {
            "values": [
                1,
                6,
                3,
                9
            ]
        },
        {
            "values": [
                8,
                2,
                5,
                3
            ]
        },
        {
            "values": []
        },
        {
            "values": []
        }
    ]
}