{
    "no": 126,
    "maxWaterInTube": 4,
    "map": [
        {
            "values": [
                6,
                7,
                11,
                7
            ]
        },
        {
            "values": [
                5,
                6,
                5,
                3
            ]
        },
        {
            "values": [
                12,
                2,
                9,
                7
            ]
        },
        {
            "values": [
                5,
                8,
                10,
                12
            ]
        },
        {
            "values": [
                9,
                3,
                11,
                9
            ]
        },
        {
            "values": [
                1,
                6,
                4,
                10
            ]
        },
        {
            "values": [
                8,
                3,
                4,
                12
            ]
        },
        {
            "values": [
                2,
                11,
                10,
                3
            ]
        },
        {
            "values": [
                4,
                7,
                1,
                2
            ]
        },
        {
            "values": [
                8,
                9,
                1,
                11
            ]
        },
        {
            "values": [
                5,
                6,
                2,
                1
            ]
        },
        {
            "values": [
                10,
                4,
                8,
                12
            ]
        },
        {
            "values": []
        },
        {
            "values": []
        }
    ]
}