{
    "no": 24,
    "maxWaterInTube": 4,
    "map": [
        {
            "values": [
                3,
                2,
                3,
                1
            ]
        },
        {
            "values": [
                4,
                2,
                3,
                0
            ]
        },
        {
            "values": [
                2,
                1,
                1,
                1
            ]
        },
        {
            "values": [
                4,
                4,
                0,
                0
            ]
        },
        {
            "values": [
                2,
                4,
                0,
                3
            ]
        },
        {
            "values": []
        },
        {
            "values": []
        }
    ]
}