{
    "no": 3038,
    "maxWaterInTube": 4,
    "map": [
        {
            "values": [
                3,
                5,
                2,
                6
            ]
        },
        {
            "values": [
                7,
                10,
                9,
                6
            ]
        },
        {
            "values": [
                0,
                11,
                10,
                7
            ]
        },
        {
            "values": [
                1,
                2,
                9,
                8
            ]
        },
        {
            "values": [
                4,
                5,
                2,
                0
            ]
        },
        {
            "values": [
                9,
                8,
                1,
                0
            ]
        },
        {
            "values": [
                11,
                6,
                0,
                4
            ]
        },
        {
            "values": [
                8,
                11,
                4,
                3
            ]
        },
        {
            "values": [
                1,
                7,
                6,
                7
            ]
        },
        {
            "values": [
                5,
                3,
                11,
                3
            ]
        },
        {
            "values": [
                9,
                5,
                2,
                10
            ]
        },
        {
            "values": [
                8,
                4,
                1,
                10
            ]
        },
        {
            "values": []
        },
        {
            "values": []
        }
    ]
}