{
    "no": 3910,
    "maxWaterInTube": 4,
    "map": [
        {
            "values": [
                7,
                2,
                9,
                10
            ]
        },
        {
            "values": [
                8,
                10,
                11,
                11
            ]
        },
        {
            "values": [
                7,
                10,
                7,
                5
            ]
        },
        {
            "values": [
                3,
                6,
                0,
                0
            ]
        },
        {
            "values": [
                0,
                2,
                1,
                1
            ]
        },
        {
            "values": [
                4,
                4,
                6,
                3
            ]
        },
        {
            "values": [
                5,
                6,
                2,
                9
            ]
        },
        {
            "values": [
                5,
                11,
                9,
                10
            ]
        },
        {
            "values": [
                7,
                2,
                3,
                9
            ]
        },
        {
            "values": [
                4,
                1,
                8,
                8
            ]
        },
        {
            "values": [
                1,
                0,
                6,
                3
            ]
        },
        {
            "values": [
                4,
                5,
                11,
                8
            ]
        },
        {
            "values": []
        },
        {
            "values": []
        }
    ]
}