{
    "no": 4256,
    "maxWaterInTube": 4,
    "map": [
        {
            "values": [
                8,
                4,
                2,
                1
            ]
        },
        {
            "values": [
                0,
                6,
                0,
                8
            ]
        },
        {
            "values": [
                10,
                0,
                9,
                3
            ]
        },
        {
            "values": [
                7,
                11,
                11,
                3
            ]
        },
        {
            "values": [
                9,
                6,
                1,
                6
            ]
        },
        {
            "values": [
                7,
                10,
                7,
                2
            ]
        },
        {
            "values": [
                0,
                5,
                9,
                11
            ]
        },
        {
            "values": [
                3,
                5,
                4,
                1
            ]
        },
        {
            "values": [
                1,
                11,
                4,
                2
            ]
        },
        {
            "values": [
                5,
                10,
                9,
                3
            ]
        },
        {
            "values": [
                5,
                2,
                10,
                8
            ]
        },
        {
            "values": [
                7,
                4,
                8,
                6
            ]
        },
        {
            "values": []
        },
        {
            "values": []
        }
    ]
}